nmea/__init__.py
nmea/data_frame.py
nmea/database_wrapper.py
nmea/input_stream.py
nmea/nmea_message.py
nmea/sv_obs.py
nmea/util.py
nmea_parser-0.5.0.dist-info/LICENSE
nmea_parser-0.5.0.dist-info/METADATA
nmea_parser-0.5.0.dist-info/WHEEL
nmea_parser-0.5.0.dist-info/top_level.txt
nmea_parser-0.5.0.dist-info/RECORD
