Metadata-Version: 2.1
Name: nmea-parser
Version: 0.5.0
Summary: Python library to parse NMEA streams
Home-page: https://gitlab.com/bek3/nmea-parser
Author: Brendan Kristiansen
Author-email: b@bek.sh
License: Mozilla Public License 2.0
Project-URL: Documentation, https://www.bek.sh/nmea-parser
Project-URL: Source Code, https://gitlab.com/bek3/nmea_parser
Platform: UNKNOWN
Classifier: Operating System :: OS Independent
Classifier: Development Status :: 4 - Beta
Classifier: Intended Audience :: Developers
Classifier: Intended Audience :: Science/Research
Classifier: Programming Language :: Python :: 3
Classifier: Programming Language :: Python :: 3.6
Classifier: Programming Language :: Python :: 3.7
Classifier: Programming Language :: Python :: 3.8
Classifier: Programming Language :: Python :: 3.9
Classifier: Topic :: Utilities
Classifier: Topic :: Software Development :: Libraries :: Python Modules
Classifier: Topic :: Scientific/Engineering :: GIS
Requires-Dist: pyserial
